musicgpt/__init__.py
musicgpt/__main__.py
musicgpt/client.py
musicgpt/schema.py
musicgpt/utils/exceptions.py
musicgpt/utils/logger.py
musicgpt/utils/stringUtils.py
musicgpt-0.0.0.dist-info/licenses/LICENSE.txt
musicgpt-0.0.0.dist-info/METADATA
musicgpt-0.0.0.dist-info/WHEEL
musicgpt-0.0.0.dist-info/top_level.txt
musicgpt-0.0.0.dist-info/RECORD
