Metadata-Version: 2.4
Name: musicgpt
Version: 0.0.0
Summary: Python package for musicgpt
Author-email: Sakar <sakar@lalals.com>
License: Proprietary - Only for users of https://musicgpt.com
Requires-Python: >=3.8
License-File: LICENSE.txt
Requires-Dist: requests>=2.0.0
Requires-Dist: pydantic>=2.0.0
Provides-Extra: dev
Requires-Dist: pytest; extra == "dev"
Requires-Dist: setuptools; extra == "dev"
Requires-Dist: wheel; extra == "dev"
Requires-Dist: requests; extra == "dev"
Requires-Dist: pydantic; extra == "dev"
Dynamic: license-file
